{
    "league_scores": [
        {
            "B365A": "2.6", 
            "B365D": "3.3", 
            "B365H": "2.8", 
            "awayTeamName": "Hoffenheim", 
            "date": "2017-01-21", 
            "goalsAwayTeam": "2", 
            "goalsHomeTeam": "0", 
            "homeTeamName": "Augsburg", 
            "league": "BL"
        }, 
        {
            "B365A": "1.91", 
            "B365D": "3.6", 
            "B365H": "4", 
            "awayTeamName": "M'gladbach", 
            "date": "2017-01-21", 
            "goalsAwayTeam": "0", 
            "goalsHomeTeam": "0", 
            "homeTeamName": "Darmstadt", 
            "league": "BL"
        }, 
        {
            "B365A": "6", 
            "B365D": "3.8", 
            "B365H": "1.62", 
            "awayTeamName": "Ein Frankfurt", 
            "date": "2017-01-21", 
            "goalsAwayTeam": "0", 
            "goalsHomeTeam": "3", 
            "homeTeamName": "RB Leipzig", 
            "league": "BL"
        }, 
        {
            "B365A": "4.75", 
            "B365D": "3.6", 
            "B365H": "1.8", 
            "awayTeamName": "Ingolstadt", 
            "date": "2017-01-21", 
            "goalsAwayTeam": "0", 
            "goalsHomeTeam": "1", 
            "homeTeamName": "Schalke 04", 
            "league": "BL"
        }, 
        {
            "B365A": "1.53", 
            "B365D": "4.33", 
            "B365H": "6", 
            "awayTeamName": "Dortmund", 
            "date": "2017-01-21", 
            "goalsAwayTeam": "2", 
            "goalsHomeTeam": "1", 
            "homeTeamName": "Werder Bremen", 
            "league": "BL"
        }, 
        {
            "B365A": "4.33", 
            "B365D": "3.6", 
            "B365H": "1.85", 
            "awayTeamName": "Hamburg", 
            "date": "2017-01-21", 
            "goalsAwayTeam": "0", 
            "goalsHomeTeam": "1", 
            "homeTeamName": "Wolfsburg", 
            "league": "BL"
        }
    ], 
    "time_end": "2017-01-21", 
    "time_start": "2017-01-21"
}
