{
    "league_scores": [
        {
            "B365A": "29", 
            "B365D": "11", 
            "B365H": "1.06", 
            "awayTeamName": "Cordoba", 
            "date": "2014-08-25", 
            "goalsAwayTeam": "0", 
            "goalsHomeTeam": "2", 
            "homeTeamName": "Real Madrid", 
            "league": "PD"
        }, 
        {
            "B365A": "1.5", 
            "B365D": "4", 
            "B365H": "7", 
            "awayTeamName": "Ath Madrid", 
            "date": "2014-08-25", 
            "goalsAwayTeam": "0", 
            "goalsHomeTeam": "0", 
            "homeTeamName": "Vallecano", 
            "league": "PD"
        }
    ], 
    "time_end": "2014-08-25", 
    "time_start": "2014-08-25"
}
